{
  "Version": 3,
  "Meta": {
    "Duration": 2.0,
    "Fps": 30.0,
    "Loop": true,
    "AreBeziersRestricted": true,
    "CurveCount": 95,
    "TotalSegmentCount": 177,
    "TotalPointCount": 209,
    "UserDataCount": 0,
    "TotalUserDataSize": 0
  },
  "Curves": [
    {
      "Target": "Parameter",
      "Id": "PARAM_ANGLE_X",
      "Segments": [
        0,
        -4.404,
        0,
        0.367,
        -12,
        0,
        0.767,
        -5,
        2,
        0.9,
        -5,
        0,
        1.267,
        -14,
        2,
        2,
        -14
      ]
    },
    {
      "Target": "Parameter",
      "Id": "PARAM_ANGLE_Y",
      "Segments": [
        0,
        -8.375,
        0,
        0.367,
        -28.805,
        1,
        0.5,
        -30,
        0.634,
        -30,
        0.767,
        -30,
        2,
        0.933,
        -30,
        0,
        1.3,
        -20.073,
        0,
        1.6,
        -25,
        2,
        2,
        -25
      ]
    },
    {
      "Target": "Parameter",
      "Id": "PARAM_ANGLE_Z",
      "Segments": [
        0,
        -15,
        0,
        0.467,
        -30,
        0,
        0.967,
        0,
        0,
        1.367,
        -23,
        0,
        1.667,
        -21.058,
        2,
        2,
        -21.058
      ]
    },
    {
      "Target": "Parameter",
      "Id": "PARAM_EYE_L_OPEN",
      "Segments": [
        0,
        1,
        2,
        1.1,
        1,
        0,
        1.2,
        0,
        2,
        2,
        0
      ]
    },
    {
      "Target": "Parameter",
      "Id": "PARAM_EYE_BALL_X",
      "Segments": [
        0,
        0.1,
        0,
        0.767,
        0,
        0,
        1.3,
        0.4,
        2,
        2,
        0.4
      ]
    },
    {
      "Target": "Parameter",
      "Id": "PARAM_EYE_BALL_Y",
      "Segments": [
        0,
        0.08,
        0,
        0.767,
        0,
        1,
        0.945,
        -0.057,
        1.122,
        -0.4,
        1.3,
        -0.4,
        2,
        2,
        -0.4
      ]
    },
    {
      "Target": "Parameter",
      "Id": "PARAM_BROW_R_FORM",
      "Segments": [
        0,
        0,
        2,
        1.1,
        0,
        0,
        1.3,
        1,
        2,
        2,
        1
      ]
    },
    {
      "Target": "Parameter",
      "Id": "PARAM_BROW_L_FORM",
      "Segments": [
        0,
        0,
        2,
        1.1,
        0,
        0,
        1.3,
        -1,
        2,
        2,
        -1
      ]
    },
    {
      "Target": "Parameter",
      "Id": "PARAM_MOUTH_OPEN_Y",
      "Segments": [
        0,
        0,
        2,
        0.933,
        0,
        0,
        1.133,
        1,
        0,
        1.467,
        0,
        2,
        2,
        0
      ]
    },
    {
      "Target": "Parameter",
      "Id": "PARAM_SHOULDER_R_ROTATE",
      "Segments": [
        0,
        1.292,
        0,
        0.133,
        3.763,
        0,
        0.533,
        0.256,
        2,
        0.7,
        0.256,
        0,
        1.233,
        -19.203,
        0,
        1.5,
        -19.09,
        2,
        2,
        -19.09
      ]
    },
    {
      "Target": "Parameter",
      "Id": "PARAM_ARM_R_ROTATE",
      "Segments": [
        0,
        0.731,
        0,
        0.233,
        -1,
        1,
        0.333,
        -1,
        0.433,
        -0.479,
        0.533,
        0.518,
        1,
        0.6,
        1.183,
        0.666,
        1.134,
        0.733,
        2.469,
        1,
        0.9,
        5.807,
        1.066,
        12.005,
        1.233,
        12.005,
        0,
        1.5,
        10.951,
        2,
        2,
        10.951
      ]
    },
    {
      "Target": "Parameter",
      "Id": "PARAM_HAND_R_ROTATE",
      "Segments": [
        0,
        9.796,
        1,
        0.144,
        9.796,
        0.289,
        -8.146,
        0.433,
        -9.06,
        0,
        0.9,
        9,
        0,
        1.233,
        8,
        0,
        1.5,
        13,
        2,
        2,
        13
      ]
    },
    {
      "Target": "Parameter",
      "Id": "PARAM_SHOULDER_L_ROTATE",
      "Segments": [
        0,
        -4.508,
        0,
        0.333,
        -2.1,
        1,
        0.455,
        -2.1,
        0.578,
        -11.768,
        0.7,
        -20,
        1,
        0.833,
        -28.981,
        0.967,
        -30.694,
        1.1,
        -30.694,
        1,
        1.233,
        -30.694,
        1.367,
        -27.247,
        1.5,
        -26.555,
        1,
        1.622,
        -25.922,
        1.745,
        -26.025,
        1.867,
        -26.025,
        2,
        2,
        -26.025
      ]
    },
    {
      "Target": "Parameter",
      "Id": "PARAM_ARM_L_ROTATE",
      "Segments": [
        0,
        2.418,
        0,
        0.4,
        -0.46,
        1,
        0.522,
        -0.46,
        0.645,
        2.97,
        0.767,
        13.367,
        1,
        0.889,
        23.764,
        1.011,
        31.35,
        1.133,
        31.35,
        0,
        1.333,
        30.367,
        0,
        1.567,
        31,
        2,
        2,
        31
      ]
    },
    {
      "Target": "Parameter",
      "Id": "PARAM_HAND_L_ROTATE",
      "Segments": [
        0,
        9.325,
        0,
        0.4,
        4.71,
        0,
        0.767,
        7.158,
        1,
        0.9,
        7.158,
        1.034,
        6.052,
        1.167,
        2,
        1,
        1.278,
        -1.377,
        1.389,
        -4.553,
        1.5,
        -4.553,
        0,
        1.867,
        -4,
        2,
        2,
        -4
      ]
    },
    {
      "Target": "Parameter",
      "Id": "PARAM_BODY_ANGLE_X",
      "Segments": [
        0,
        -4.286,
        0,
        0.667,
        10,
        0,
        1.233,
        -10,
        2,
        2,
        -10
      ]
    },
    {
      "Target": "Parameter",
      "Id": "PARAM_BODY_ANGLE_Y",
      "Segments": [
        0,
        1.056,
        0,
        0.533,
        6,
        1,
        0.744,
        9.114,
        0.956,
        10,
        1.167,
        10,
        0,
        1.5,
        9.353,
        2,
        2,
        9.353
      ]
    },
    {
      "Target": "Parameter",
      "Id": "PARAM_BODY_ANGLE_Z",
      "Segments": [
        0,
        4.98,
        1,
        0.178,
        4.98,
        0.355,
        9.435,
        0.533,
        6,
        0,
        1.167,
        -8,
        0,
        1.5,
        -7.5,
        2,
        2,
        -7.5
      ]
    },
    {
      "Target": "Parameter",
      "Id": "PARAM_STRETCH",
      "Segments": [
        0,
        -0.1,
        0,
        0.533,
        -0.4,
        0,
        1.167,
        0,
        2,
        2,
        0
      ]
    },
    {
      "Target": "Parameter",
      "Id": "PARAM_SHOLDER_POSITION",
      "Segments": [
        0,
        -7.944,
        0,
        0.533,
        -10,
        0,
        1.167,
        2,
        0,
        1.5,
        0,
        2,
        2,
        0
      ]
    },
    {
      "Target": "Parameter",
      "Id": "PARAM_POSITION_Y",
      "Segments": [
        0,
        0,
        0,
        0.533,
        -0.268,
        0,
        0.967,
        0.081,
        0,
        1.233,
        -0.043,
        0,
        1.467,
        0,
        2,
        2,
        0
      ]
    },
    {
      "Target": "Parameter",
      "Id": "PARAM_ROTATION_Z",
      "Segments": [
        0,
        -0.5,
        0,
        1.2,
        1,
        2,
        2,
        1
      ]
    },
    {
      "Target": "Parameter",
      "Id": "PARAM_HAND_R_01",
      "Segments": [
        0,
        1,
        2,
        0.8,
        1,
        0,
        0.833,
        0,
        2,
        2,
        0
      ]
    },
    {
      "Target": "Parameter",
      "Id": "PARAM_HAND_R_04",
      "Segments": [
        0,
        0,
        2,
        0.8,
        0,
        0,
        0.833,
        1,
        2,
        2,
        1
      ]
    },
    {
      "Target": "Parameter",
      "Id": "PARAM_HAND_L_01",
      "Segments": [
        0,
        1,
        2,
        0.8,
        1,
        0,
        0.833,
        0,
        2,
        2,
        0
      ]
    },
    {
      "Target": "Parameter",
      "Id": "PARAM_HAND_L_05",
      "Segments": [
        0,
        0,
        2,
        0.8,
        0,
        0,
        0.833,
        1,
        2,
        2,
        1
      ]
    },
    {
      "Target": "Model",
      "Id": "Opacity",
      "Segments": [
        0,
        1,
        0,
        2,
        1
      ]
    },
    {
      "Target": "Parameter",
      "Id": "PARAM_EYE_R_OPEN",
      "Segments": [
        0,
        1,
        0,
        2,
        1
      ]
    },
    {
      "Target": "Parameter",
      "Id": "PARAM_EYE_R_SMILE",
      "Segments": [
        0,
        0,
        0,
        2,
        0
      ]
    },
    {
      "Target": "Parameter",
      "Id": "PARAM_EYE_L_SMILE",
      "Segments": [
        0,
        0,
        0,
        2,
        0
      ]
    },
    {
      "Target": "Parameter",
      "Id": "PARAM_EYE_FORM",
      "Segments": [
        0,
        0,
        0,
        2,
        0
      ]
    },
    {
      "Target": "Parameter",
      "Id": "PARAM_EYE_SCALE",
      "Segments": [
        0,
        0,
        0,
        2,
        0
      ]
    },
    {
      "Target": "Parameter",
      "Id": "PARAM_TEAR_LEAP_01",
      "Segments": [
        0,
        0,
        0,
        2,
        0
      ]
    },
    {
      "Target": "Parameter",
      "Id": "PARAM_BROW_R_X",
      "Segments": [
        0,
        0,
        0,
        2,
        0
      ]
    },
    {
      "Target": "Parameter",
      "Id": "PARAM_BROW_R_Y",
      "Segments": [
        0,
        0,
        0,
        2,
        0
      ]
    },
    {
      "Target": "Parameter",
      "Id": "PARAM_BROW_R_ANGLE",
      "Segments": [
        0,
        0,
        0,
        2,
        0
      ]
    },
    {
      "Target": "Parameter",
      "Id": "PARAM_BROW_L_X",
      "Segments": [
        0,
        0,
        0,
        2,
        0
      ]
    },
    {
      "Target": "Parameter",
      "Id": "PARAM_BROW_L_Y",
      "Segments": [
        0,
        0,
        0,
        2,
        0
      ]
    },
    {
      "Target": "Parameter",
      "Id": "PARAM_BROW_L_ANGLE",
      "Segments": [
        0,
        0,
        0,
        2,
        0
      ]
    },
    {
      "Target": "Parameter",
      "Id": "PARAM_MOUTH_FORM_01",
      "Segments": [
        0,
        1,
        0,
        2,
        1
      ]
    },
    {
      "Target": "Parameter",
      "Id": "PARAM_MOUTH_POS_Y",
      "Segments": [
        0,
        0,
        0,
        2,
        0
      ]
    },
    {
      "Target": "Parameter",
      "Id": "PARAM_MOUTH_SCALE",
      "Segments": [
        0,
        0.5,
        0,
        2,
        0.5
      ]
    },
    {
      "Target": "Parameter",
      "Id": "PARAM_MOUTH_SCALE_Y",
      "Segments": [
        0,
        0,
        0,
        2,
        0
      ]
    },
    {
      "Target": "Parameter",
      "Id": "PARAM_ARM_R_ORDER",
      "Segments": [
        0,
        1,
        0,
        2,
        1
      ]
    },
    {
      "Target": "Parameter",
      "Id": "PARAM_ARM_L_ORDER",
      "Segments": [
        0,
        1,
        0,
        2,
        1
      ]
    },
    {
      "Target": "Parameter",
      "Id": "PARAM_BREATH",
      "Segments": [
        0,
        0,
        0,
        2,
        0
      ]
    },
    {
      "Target": "Parameter",
      "Id": "PARAM_POSITION_X",
      "Segments": [
        0,
        0,
        0,
        2,
        0
      ]
    },
    {
      "Target": "Parameter",
      "Id": "PARAM_BAST_SHAKE",
      "Segments": [
        0,
        0,
        0,
        2,
        0
      ]
    },
    {
      "Target": "Parameter",
      "Id": "PARAM_HAIR_FRONT",
      "Segments": [
        0,
        -0.028,
        0,
        2,
        -0.028
      ]
    },
    {
      "Target": "Parameter",
      "Id": "PARAM_HAIR_SIDE",
      "Segments": [
        0,
        -0.022,
        0,
        2,
        -0.022
      ]
    },
    {
      "Target": "Parameter",
      "Id": "PARAM_HAIR_BACK_01",
      "Segments": [
        0,
        -0.051,
        0,
        2,
        -0.051
      ]
    },
    {
      "Target": "Parameter",
      "Id": "PARAM_HAIR_BACK_02",
      "Segments": [
        0,
        0,
        0,
        2,
        0
      ]
    },
    {
      "Target": "Parameter",
      "Id": "PARAM_FLUFFY",
      "Segments": [
        0,
        -0.011,
        0,
        2,
        -0.011
      ]
    },
    {
      "Target": "Parameter",
      "Id": "PARAM_FACE_SHADOW",
      "Segments": [
        0,
        0,
        0,
        2,
        0
      ]
    },
    {
      "Target": "Parameter",
      "Id": "PARAM_FACE_CHANGE",
      "Segments": [
        0,
        0,
        0,
        2,
        0
      ]
    },
    {
      "Target": "Parameter",
      "Id": "PARAM_CHEEK_01",
      "Segments": [
        0,
        1,
        0,
        2,
        1
      ]
    },
    {
      "Target": "Parameter",
      "Id": "PARAM_CHEEK_02",
      "Segments": [
        0,
        0,
        0,
        2,
        0
      ]
    },
    {
      "Target": "Parameter",
      "Id": "PARAM_CHEEK_03",
      "Segments": [
        0,
        0,
        0,
        2,
        0
      ]
    },
    {
      "Target": "Parameter",
      "Id": "PARAM_CHEEK_04",
      "Segments": [
        0,
        0,
        0,
        2,
        0
      ]
    },
    {
      "Target": "Parameter",
      "Id": "PARAM_CHEEK_05",
      "Segments": [
        0,
        0,
        0,
        2,
        0
      ]
    },
    {
      "Target": "Parameter",
      "Id": "PARAM_TEAR_01",
      "Segments": [
        0,
        0,
        0,
        2,
        0
      ]
    },
    {
      "Target": "Parameter",
      "Id": "PARAM_TEAR_02",
      "Segments": [
        0,
        0,
        0,
        2,
        0
      ]
    },
    {
      "Target": "Parameter",
      "Id": "PARAM_TEAR_02_MOVE",
      "Segments": [
        0,
        0,
        0,
        2,
        0
      ]
    },
    {
      "Target": "Parameter",
      "Id": "PARAM_TEAR_03",
      "Segments": [
        0,
        0,
        0,
        2,
        0
      ]
    },
    {
      "Target": "Parameter",
      "Id": "PARAM_TEAR_03_MOVE",
      "Segments": [
        0,
        0,
        0,
        2,
        0
      ]
    },
    {
      "Target": "Parameter",
      "Id": "PARAM_SWEAT",
      "Segments": [
        0,
        0,
        0,
        2,
        0
      ]
    },
    {
      "Target": "Parameter",
      "Id": "PARAM_SWEAT_MOVE",
      "Segments": [
        0,
        0,
        0,
        2,
        0
      ]
    },
    {
      "Target": "Parameter",
      "Id": "PARAM_EYE_WHITE_00",
      "Segments": [
        0,
        1,
        0,
        2,
        1
      ]
    },
    {
      "Target": "Parameter",
      "Id": "PARAM_EYE_WHITE_01",
      "Segments": [
        0,
        0,
        0,
        2,
        0
      ]
    },
    {
      "Target": "Parameter",
      "Id": "PARAM_EYE_01",
      "Segments": [
        0,
        1,
        0,
        2,
        1
      ]
    },
    {
      "Target": "Parameter",
      "Id": "PARAM_EYE_02",
      "Segments": [
        0,
        0,
        0,
        2,
        0
      ]
    },
    {
      "Target": "Parameter",
      "Id": "PARAM_EYE_05",
      "Segments": [
        0,
        0,
        0,
        2,
        0
      ]
    },
    {
      "Target": "Parameter",
      "Id": "PARAM_MOUTH_01",
      "Segments": [
        0,
        1,
        0,
        2,
        1
      ]
    },
    {
      "Target": "Parameter",
      "Id": "PARAM_MOUTH_02",
      "Segments": [
        0,
        0,
        0,
        2,
        0
      ]
    },
    {
      "Target": "Parameter",
      "Id": "PARAM_MOUTH_03",
      "Segments": [
        0,
        0,
        0,
        2,
        0
      ]
    },
    {
      "Target": "Parameter",
      "Id": "PARAM_MOUTH_05",
      "Segments": [
        0,
        0,
        0,
        2,
        0
      ]
    },
    {
      "Target": "Parameter",
      "Id": "PARAM_BROW_01",
      "Segments": [
        0,
        1,
        0,
        2,
        1
      ]
    },
    {
      "Target": "Parameter",
      "Id": "PARAM_HAND_R_02",
      "Segments": [
        0,
        0,
        0,
        2,
        0
      ]
    },
    {
      "Target": "Parameter",
      "Id": "PARAM_HAND_R_03",
      "Segments": [
        0,
        0,
        0,
        2,
        0
      ]
    },
    {
      "Target": "Parameter",
      "Id": "PARAM_HAND_R_05",
      "Segments": [
        0,
        0,
        0,
        2,
        0
      ]
    },
    {
      "Target": "Parameter",
      "Id": "PARAM_HAND_R_06",
      "Segments": [
        0,
        0,
        0,
        2,
        0
      ]
    },
    {
      "Target": "Parameter",
      "Id": "PARAM_HAND_R_07",
      "Segments": [
        0,
        0,
        0,
        2,
        0
      ]
    },
    {
      "Target": "Parameter",
      "Id": "PARAM_HAND_R_08",
      "Segments": [
        0,
        0,
        0,
        2,
        0
      ]
    },
    {
      "Target": "Parameter",
      "Id": "PARAM_HAND_R_09",
      "Segments": [
        0,
        0,
        0,
        2,
        0
      ]
    },
    {
      "Target": "Parameter",
      "Id": "PARAM_HAND_R_10",
      "Segments": [
        0,
        0,
        0,
        2,
        0
      ]
    },
    {
      "Target": "Parameter",
      "Id": "PARAM_HAND_R_11",
      "Segments": [
        0,
        0,
        0,
        2,
        0
      ]
    },
    {
      "Target": "Parameter",
      "Id": "PARAM_HAND_L_02",
      "Segments": [
        0,
        0,
        0,
        2,
        0
      ]
    },
    {
      "Target": "Parameter",
      "Id": "PARAM_HAND_L_03",
      "Segments": [
        0,
        0,
        0,
        2,
        0
      ]
    },
    {
      "Target": "Parameter",
      "Id": "PARAM_HAND_L_04",
      "Segments": [
        0,
        0,
        0,
        2,
        0
      ]
    },
    {
      "Target": "Parameter",
      "Id": "PARAM_HAND_L_06",
      "Segments": [
        0,
        0,
        0,
        2,
        0
      ]
    },
    {
      "Target": "Parameter",
      "Id": "PARAM_HAND_L_07",
      "Segments": [
        0,
        0,
        0,
        2,
        0
      ]
    },
    {
      "Target": "Parameter",
      "Id": "PARAM_HAND_L_08",
      "Segments": [
        0,
        0,
        0,
        2,
        0
      ]
    },
    {
      "Target": "Parameter",
      "Id": "PARAM_HAND_L_09",
      "Segments": [
        0,
        0,
        0,
        2,
        0
      ]
    },
    {
      "Target": "Parameter",
      "Id": "PARAM_HAND_L_10",
      "Segments": [
        0,
        0,
        0,
        2,
        0
      ]
    },
    {
      "Target": "Parameter",
      "Id": "PARAM_HAND_L_11",
      "Segments": [
        0,
        0,
        0,
        2,
        0
      ]
    }
  ],
  "UserData": []
}