{
  "Version": 3,
  "Meta": {
    "Duration": 2.9,
    "Fps": 30.0,
    "Loop": true,
    "AreBeziersRestricted": true,
    "FadeInTime": 0.0,
    "FadeOutTime": 0.0,
    "CurveCount": 112,
    "TotalSegmentCount": 261,
    "TotalPointCount": 311,
    "UserDataCount": 0,
    "TotalUserDataSize": 0
  },
  "Curves": [
    {
      "Target": "Parameter",
      "Id": "PARAM_ANGLE_X",
      "FadeInTime": -1.0,
      "FadeOutTime": -1.0,
      "Segments": [
        0,
        -6.974,
        1,
        0.167,
        -6.974,
        0.333,
        -5.508,
        0.5,
        -4,
        1,
        0.6,
        -3.072,
        0.7,
        -2.394,
        0.8,
        -2,
        1,
        1.133,
        -0.522,
        1.467,
        0,
        1.8,
        0,
        2,
        2.9,
        0
      ]
    },
    {
      "Target": "Parameter",
      "Id": "PARAM_ANGLE_Y",
      "FadeInTime": -1.0,
      "FadeOutTime": -1.0,
      "Segments": [
        0,
        -12.16,
        0,
        0.467,
        -20,
        0,
        0.767,
        20.742,
        0,
        0.967,
        -10.526,
        0,
        1.367,
        6.204,
        0,
        1.767,
        4.474,
        2,
        2.9,
        4.474
      ]
    },
    {
      "Target": "Parameter",
      "Id": "PARAM_ANGLE_Z",
      "FadeInTime": -1.0,
      "FadeOutTime": -1.0,
      "Segments": [
        0,
        8.003,
        1,
        0.156,
        8.003,
        0.311,
        8.084,
        0.467,
        11,
        1,
        0.567,
        12.944,
        0.667,
        30,
        0.767,
        30,
        0,
        0.967,
        13.24,
        0,
        1.367,
        15.433,
        0,
        1.767,
        14,
        2,
        2.9,
        14
      ]
    },
    {
      "Target": "Parameter",
      "Id": "PARAM_EYE_R_OPEN",
      "FadeInTime": -1.0,
      "FadeOutTime": -1.0,
      "Segments": [
        0,
        1,
        0,
        0.333,
        1.346,
        0,
        0.433,
        0,
        2,
        0.6,
        0,
        1,
        0.633,
        0,
        0.667,
        1.07,
        0.7,
        1.298,
        1,
        0.733,
        1.382,
        0.767,
        1.48,
        0.8,
        1.498,
        2,
        2.9,
        1.498
      ]
    },
    {
      "Target": "Parameter",
      "Id": "PARAM_EYE_L_OPEN",
      "FadeInTime": -1.0,
      "FadeOutTime": -1.0,
      "Segments": [
        0,
        1,
        0,
        0.333,
        1.346,
        0,
        0.433,
        0,
        2,
        0.6,
        0,
        1,
        0.633,
        0,
        0.667,
        1.07,
        0.7,
        1.298,
        1,
        0.733,
        1.382,
        0.767,
        1.48,
        0.8,
        1.498,
        2,
        2.9,
        1.498
      ]
    },
    {
      "Target": "Parameter",
      "Id": "PARAM_EYE_FORM",
      "FadeInTime": -1.0,
      "FadeOutTime": -1.0,
      "Segments": [
        0,
        0,
        2,
        0.6,
        0,
        0,
        0.8,
        1,
        2,
        2.9,
        1
      ]
    },
    {
      "Target": "Parameter",
      "Id": "PARAM_EYE_BALL_X",
      "FadeInTime": -1.0,
      "FadeOutTime": -1.0,
      "Segments": [
        0,
        0.2,
        0,
        0.6,
        0.1,
        1,
        0.711,
        0.056,
        0.822,
        0,
        0.933,
        0,
        2,
        2.9,
        0
      ]
    },
    {
      "Target": "Parameter",
      "Id": "PARAM_EYE_BALL_Y",
      "FadeInTime": -1.0,
      "FadeOutTime": -1.0,
      "Segments": [
        0,
        0,
        0,
        0.6,
        0.1,
        0,
        0.933,
        -0.1,
        2,
        2.9,
        -0.1
      ]
    },
    {
      "Target": "Parameter",
      "Id": "PARAM_EYE_SCALE",
      "FadeInTime": -1.0,
      "FadeOutTime": -1.0,
      "Segments": [
        0,
        0,
        1,
        0.2,
        0,
        0.4,
        -0.042,
        0.6,
        0,
        1,
        0.633,
        0.007,
        0.667,
        0.2,
        0.7,
        0.2,
        0,
        0.933,
        -1,
        2,
        2.9,
        -1
      ]
    },
    {
      "Target": "Parameter",
      "Id": "PARAM_BROW_R_FORM",
      "FadeInTime": -1.0,
      "FadeOutTime": -1.0,
      "Segments": [
        0,
        -0.1,
        2,
        0.433,
        -0.1,
        0,
        0.8,
        0.3,
        2,
        2.9,
        0.3
      ]
    },
    {
      "Target": "Parameter",
      "Id": "PARAM_BROW_R_Y",
      "FadeInTime": -1.0,
      "FadeOutTime": -1.0,
      "Segments": [
        0,
        0,
        2,
        0.333,
        0,
        0,
        0.433,
        -0.4,
        2,
        0.6,
        -0.4,
        1,
        0.633,
        -0.4,
        0.667,
        -0.083,
        0.7,
        0.06,
        1,
        0.733,
        0.203,
        0.767,
        0.2,
        0.8,
        0.2,
        2,
        2.9,
        0.2
      ]
    },
    {
      "Target": "Parameter",
      "Id": "PARAM_BROW_R_ANGLE",
      "FadeInTime": -1.0,
      "FadeOutTime": -1.0,
      "Segments": [
        0,
        0,
        2,
        0.433,
        0,
        0,
        0.8,
        0.3,
        2,
        2.9,
        0.3
      ]
    },
    {
      "Target": "Parameter",
      "Id": "PARAM_BROW_L_FORM",
      "FadeInTime": -1.0,
      "FadeOutTime": -1.0,
      "Segments": [
        0,
        -0.1,
        2,
        0.433,
        -0.1,
        0,
        0.8,
        0.3,
        2,
        2.9,
        0.3
      ]
    },
    {
      "Target": "Parameter",
      "Id": "PARAM_BROW_L_Y",
      "FadeInTime": -1.0,
      "FadeOutTime": -1.0,
      "Segments": [
        0,
        0,
        2,
        0.333,
        0,
        0,
        0.433,
        -0.4,
        2,
        0.6,
        -0.4,
        1,
        0.633,
        -0.4,
        0.667,
        -0.083,
        0.7,
        0.06,
        1,
        0.733,
        0.203,
        0.767,
        0.2,
        0.8,
        0.2,
        2,
        2.9,
        0.2
      ]
    },
    {
      "Target": "Parameter",
      "Id": "PARAM_BROW_L_ANGLE",
      "FadeInTime": -1.0,
      "FadeOutTime": -1.0,
      "Segments": [
        0,
        0,
        2,
        0.433,
        0,
        0,
        0.8,
        0.3,
        2,
        2.9,
        0.3
      ]
    },
    {
      "Target": "Parameter",
      "Id": "PARAM_MOUTH_FORM_01",
      "FadeInTime": -1.0,
      "FadeOutTime": -1.0,
      "Segments": [
        0,
        -1,
        2,
        0.467,
        -1,
        0,
        0.733,
        -2,
        2,
        2.9,
        -2
      ]
    },
    {
      "Target": "Parameter",
      "Id": "PARAM_MOUTH_SCALE",
      "FadeInTime": -1.0,
      "FadeOutTime": -1.0,
      "Segments": [
        0,
        0.013,
        2,
        0.467,
        0.013,
        0,
        0.733,
        0,
        2,
        2.9,
        0
      ]
    },
    {
      "Target": "Parameter",
      "Id": "PARAM_MOUTH_SCALE_Y",
      "FadeInTime": -1.0,
      "FadeOutTime": -1.0,
      "Segments": [
        0,
        0,
        2,
        0.467,
        0,
        0,
        0.733,
        -0.6,
        2,
        2.9,
        -0.6
      ]
    },
    {
      "Target": "Parameter",
      "Id": "PARAM_SHOULDER_R_ROTATE",
      "FadeInTime": -1.0,
      "FadeOutTime": -1.0,
      "Segments": [
        0,
        -34.532,
        0,
        0.333,
        -35,
        0,
        0.667,
        -31.15,
        2,
        2.9,
        -31.15
      ]
    },
    {
      "Target": "Parameter",
      "Id": "PARAM_ARM_R_ROTATE",
      "FadeInTime": -1.0,
      "FadeOutTime": -1.0,
      "Segments": [
        0,
        18.332,
        0,
        0.367,
        18.44,
        0,
        0.667,
        18.09,
        0,
        1.067,
        18.51,
        2,
        2.9,
        18.51
      ]
    },
    {
      "Target": "Parameter",
      "Id": "PARAM_HAND_R_ROTATE",
      "FadeInTime": -1.0,
      "FadeOutTime": -1.0,
      "Segments": [
        0,
        16.62,
        2,
        0.4,
        16.62,
        0,
        0.7,
        18.54,
        0,
        1.133,
        16.5,
        2,
        2.9,
        16.5
      ]
    },
    {
      "Target": "Parameter",
      "Id": "PARAM_SHOULDER_L_ROTATE",
      "FadeInTime": -1.0,
      "FadeOutTime": -1.0,
      "Segments": [
        0,
        2.519,
        1,
        0.133,
        2.519,
        0.267,
        1.676,
        0.4,
        -3.246,
        1,
        0.467,
        -5.707,
        0.533,
        -14.43,
        0.6,
        -14.43,
        0,
        0.9,
        -5.952,
        0,
        1.3,
        -8.042,
        0,
        1.733,
        -5.622,
        2,
        2.9,
        -5.622
      ]
    },
    {
      "Target": "Parameter",
      "Id": "PARAM_ARM_L_ROTATE",
      "FadeInTime": -1.0,
      "FadeOutTime": -1.0,
      "Segments": [
        0,
        1.852,
        0,
        0.467,
        2.532,
        0,
        0.633,
        2.099,
        0,
        0.933,
        2.902,
        0,
        1.367,
        1.677,
        0,
        1.8,
        1.926,
        2,
        2.9,
        1.926
      ]
    },
    {
      "Target": "Parameter",
      "Id": "PARAM_HAND_L_ROTATE",
      "FadeInTime": -1.0,
      "FadeOutTime": -1.0,
      "Segments": [
        0,
        1.829,
        0,
        0.933,
        8.46,
        0,
        1.433,
        7.254,
        0,
        1.833,
        8.335,
        2,
        2.9,
        8.335
      ]
    },
    {
      "Target": "Parameter",
      "Id": "PARAM_BODY_ANGLE_X",
      "FadeInTime": -1.0,
      "FadeOutTime": -1.0,
      "Segments": [
        0,
        -3.111,
        0,
        0.367,
        -7,
        0,
        0.567,
        -2,
        2,
        2.9,
        -2
      ]
    },
    {
      "Target": "Parameter",
      "Id": "PARAM_BODY_ANGLE_Y",
      "FadeInTime": -1.0,
      "FadeOutTime": -1.0,
      "Segments": [
        0,
        -0.032,
        1,
        0.122,
        -0.033,
        0.245,
        -1.533,
        0.367,
        -1.533,
        1,
        0.434,
        -1.533,
        0.5,
        3.15,
        0.567,
        3.151,
        1,
        0.645,
        3.15,
        0.722,
        -0.269,
        0.8,
        -0.269,
        0,
        1.167,
        0.451,
        0,
        1.6,
        0.291,
        2,
        2.9,
        0.291
      ]
    },
    {
      "Target": "Parameter",
      "Id": "PARAM_BODY_ANGLE_Z",
      "FadeInTime": -1.0,
      "FadeOutTime": -1.0,
      "Segments": [
        0,
        -2.728,
        0,
        0.367,
        -3,
        0,
        0.567,
        4,
        0,
        0.8,
        3.84,
        2,
        2.9,
        3.84
      ]
    },
    {
      "Target": "Parameter",
      "Id": "PARAM_STRETCH",
      "FadeInTime": -1.0,
      "FadeOutTime": -1.0,
      "Segments": [
        0,
        0.057,
        0,
        0.4,
        -0.052,
        0,
        0.667,
        0.301,
        0,
        0.9,
        -0.1,
        0,
        1.267,
        0.1,
        0,
        1.7,
        0,
        2,
        2.9,
        0
      ]
    },
    {
      "Target": "Parameter",
      "Id": "PARAM_SHOLDER_POSITION",
      "FadeInTime": -1.0,
      "FadeOutTime": -1.0,
      "Segments": [
        0,
        -4.071,
        0,
        0.4,
        -7,
        0,
        0.6,
        6.946,
        0,
        0.833,
        -1.054,
        0,
        1.233,
        1.308,
        0,
        1.6,
        -7,
        2,
        2.9,
        -7
      ]
    },
    {
      "Target": "Parameter",
      "Id": "PARAM_POSITION_X",
      "FadeInTime": -1.0,
      "FadeOutTime": -1.0,
      "Segments": [
        0,
        0,
        2,
        0.367,
        0,
        0,
        0.567,
        0.13,
        2,
        2.9,
        0.13
      ]
    },
    {
      "Target": "Parameter",
      "Id": "PARAM_POSITION_Y",
      "FadeInTime": -1.0,
      "FadeOutTime": -1.0,
      "Segments": [
        0,
        0,
        2,
        0.367,
        0,
        0,
        0.567,
        0.099,
        0,
        0.8,
        0,
        2,
        2.9,
        0
      ]
    },
    {
      "Target": "Parameter",
      "Id": "PARAM_ROTATION_Z",
      "FadeInTime": -1.0,
      "FadeOutTime": -1.0,
      "Segments": [
        0,
        0.344,
        1,
        0.122,
        0.344,
        0.245,
        0.343,
        0.367,
        0.3,
        1,
        0.434,
        0.278,
        0.5,
        -0.3,
        0.567,
        -0.3,
        0,
        0.867,
        -0.278,
        2,
        2.9,
        -0.278
      ]
    },
    {
      "Target": "Parameter",
      "Id": "PARAM_HAIR_FRONT",
      "FadeInTime": -1.0,
      "FadeOutTime": -1.0,
      "Segments": [
        0,
        0.029,
        0,
        0.267,
        0.156,
        0,
        0.533,
        -0.46,
        0,
        0.833,
        0.991,
        0,
        1.167,
        -0.262,
        0,
        1.467,
        0.5,
        0,
        1.767,
        0.037,
        0,
        2.1,
        0.3,
        0,
        2.4,
        0.145,
        0,
        2.667,
        0.235,
        1,
        2.745,
        0.235,
        2.822,
        0.195,
        2.9,
        0.185
      ]
    },
    {
      "Target": "Parameter",
      "Id": "PARAM_HAIR_SIDE",
      "FadeInTime": -1.0,
      "FadeOutTime": -1.0,
      "Segments": [
        0,
        0.03,
        1,
        0.089,
        0.031,
        0.178,
        0.125,
        0.267,
        0.125,
        0,
        0.567,
        -0.334,
        0,
        0.867,
        0.831,
        0,
        1.2,
        -0.214,
        0,
        1.533,
        0.441,
        0,
        1.867,
        0.027,
        0,
        2.2,
        0.275,
        0,
        2.533,
        0.125,
        0,
        2.8,
        0.217,
        2,
        2.9,
        0.217
      ]
    },
    {
      "Target": "Parameter",
      "Id": "PARAM_HAIR_BACK_01",
      "FadeInTime": -1.0,
      "FadeOutTime": -1.0,
      "Segments": [
        0,
        0.057,
        0,
        0.3,
        0.317,
        0,
        0.567,
        -0.67,
        0,
        0.833,
        1,
        0,
        1.233,
        0.09,
        0,
        1.633,
        0.501,
        0,
        2,
        0.336,
        0,
        2.367,
        0.393,
        0,
        2.7,
        0.373,
        2,
        2.9,
        0.373
      ]
    },
    {
      "Target": "Parameter",
      "Id": "PARAM_HAIR_BACK_02",
      "FadeInTime": -1.0,
      "FadeOutTime": -1.0,
      "Segments": [
        0,
        -0.01,
        0,
        0.233,
        -0.14,
        0,
        0.533,
        0.711,
        0,
        0.767,
        -1,
        2,
        0.867,
        -1,
        0,
        1.133,
        0.82,
        0,
        1.467,
        -0.386,
        0,
        1.833,
        0.158,
        0,
        2.2,
        -0.058,
        0,
        2.6,
        0.021,
        0,
        2.867,
        -0.007,
        2,
        2.9,
        -0.007
      ]
    },
    {
      "Target": "Parameter",
      "Id": "PARAM_FLUFFY",
      "FadeInTime": -1.0,
      "FadeOutTime": -1.0,
      "Segments": [
        0,
        0.009,
        0,
        0.333,
        0.083,
        0,
        0.7,
        -0.289,
        0,
        1,
        0.531,
        0,
        1.4,
        -0.123,
        0,
        1.9,
        0.176,
        0,
        2.367,
        0.035,
        0,
        2.8,
        0.104,
        2,
        2.9,
        0.104
      ]
    },
    {
      "Target": "Model",
      "Id": "Opacity",
      "FadeInTime": -1.0,
      "FadeOutTime": -1.0,
      "Segments": [
        0,
        1,
        0,
        2.9,
        1
      ]
    },
    {
      "Target": "Parameter",
      "Id": "PARAM_EYE_R_SMILE",
      "FadeInTime": -1.0,
      "FadeOutTime": -1.0,
      "Segments": [
        0,
        0,
        0,
        2.9,
        0
      ]
    },
    {
      "Target": "Parameter",
      "Id": "PARAM_EYE_L_SMILE",
      "FadeInTime": -1.0,
      "FadeOutTime": -1.0,
      "Segments": [
        0,
        0,
        0,
        2.9,
        0
      ]
    },
    {
      "Target": "Parameter",
      "Id": "PARAM_TEAR_LEAP_01",
      "FadeInTime": -1.0,
      "FadeOutTime": -1.0,
      "Segments": [
        0,
        0,
        0,
        2.9,
        0
      ]
    },
    {
      "Target": "Parameter",
      "Id": "PARAM_BROW_R_X",
      "FadeInTime": -1.0,
      "FadeOutTime": -1.0,
      "Segments": [
        0,
        0,
        0,
        2.9,
        0
      ]
    },
    {
      "Target": "Parameter",
      "Id": "PARAM_BROW_L_X",
      "FadeInTime": -1.0,
      "FadeOutTime": -1.0,
      "Segments": [
        0,
        0,
        0,
        2.9,
        0
      ]
    },
    {
      "Target": "Parameter",
      "Id": "PARAM_MOUTH_OPEN_Y",
      "FadeInTime": -1.0,
      "FadeOutTime": -1.0,
      "Segments": [
        0,
        0,
        0,
        2.9,
        0
      ]
    },
    {
      "Target": "Parameter",
      "Id": "PARAM_MOUTH_POS_Y",
      "FadeInTime": -1.0,
      "FadeOutTime": -1.0,
      "Segments": [
        0,
        -0.1,
        0,
        2.9,
        -0.1
      ]
    },
    {
      "Target": "Parameter",
      "Id": "PARAM_ARM_R_ORDER",
      "FadeInTime": -1.0,
      "FadeOutTime": -1.0,
      "Segments": [
        0,
        1,
        0,
        2.9,
        1
      ]
    },
    {
      "Target": "Parameter",
      "Id": "PARAM_ARM_L_ORDER",
      "FadeInTime": -1.0,
      "FadeOutTime": -1.0,
      "Segments": [
        0,
        0,
        0,
        2.9,
        0
      ]
    },
    {
      "Target": "Parameter",
      "Id": "PARAM_BREATH",
      "FadeInTime": -1.0,
      "FadeOutTime": -1.0,
      "Segments": [
        0,
        0,
        0,
        2.9,
        0
      ]
    },
    {
      "Target": "Parameter",
      "Id": "PARAM_BAST_SHAKE",
      "FadeInTime": -1.0,
      "FadeOutTime": -1.0,
      "Segments": [
        0,
        0,
        0,
        2.9,
        0
      ]
    },
    {
      "Target": "Parameter",
      "Id": "PARAM_FACE_SHADOW",
      "FadeInTime": -1.0,
      "FadeOutTime": -1.0,
      "Segments": [
        0,
        0,
        0,
        2.9,
        0
      ]
    },
    {
      "Target": "Parameter",
      "Id": "PARAM_FACE_CHANGE",
      "FadeInTime": -1.0,
      "FadeOutTime": -1.0,
      "Segments": [
        0,
        0,
        0,
        2.9,
        0
      ]
    },
    {
      "Target": "Parameter",
      "Id": "PARAM_CHEEK_01",
      "FadeInTime": -1.0,
      "FadeOutTime": -1.0,
      "Segments": [
        0,
        1,
        0,
        2.9,
        1
      ]
    },
    {
      "Target": "Parameter",
      "Id": "PARAM_CHEEK_02",
      "FadeInTime": -1.0,
      "FadeOutTime": -1.0,
      "Segments": [
        0,
        0,
        0,
        2.9,
        0
      ]
    },
    {
      "Target": "Parameter",
      "Id": "PARAM_CHEEK_03",
      "FadeInTime": -1.0,
      "FadeOutTime": -1.0,
      "Segments": [
        0,
        0,
        0,
        2.9,
        0
      ]
    },
    {
      "Target": "Parameter",
      "Id": "PARAM_CHEEK_04",
      "FadeInTime": -1.0,
      "FadeOutTime": -1.0,
      "Segments": [
        0,
        0,
        0,
        2.9,
        0
      ]
    },
    {
      "Target": "Parameter",
      "Id": "PARAM_CHEEK_05",
      "FadeInTime": -1.0,
      "FadeOutTime": -1.0,
      "Segments": [
        0,
        0,
        0,
        2.9,
        0
      ]
    },
    {
      "Target": "Parameter",
      "Id": "PARAM_TEAR_01",
      "FadeInTime": -1.0,
      "FadeOutTime": -1.0,
      "Segments": [
        0,
        0,
        0,
        2.9,
        0
      ]
    },
    {
      "Target": "Parameter",
      "Id": "PARAM_TEAR_02",
      "FadeInTime": -1.0,
      "FadeOutTime": -1.0,
      "Segments": [
        0,
        0,
        0,
        2.9,
        0
      ]
    },
    {
      "Target": "Parameter",
      "Id": "PARAM_TEAR_02_MOVE",
      "FadeInTime": -1.0,
      "FadeOutTime": -1.0,
      "Segments": [
        0,
        0,
        0,
        2.9,
        0
      ]
    },
    {
      "Target": "Parameter",
      "Id": "PARAM_TEAR_03",
      "FadeInTime": -1.0,
      "FadeOutTime": -1.0,
      "Segments": [
        0,
        0,
        0,
        2.9,
        0
      ]
    },
    {
      "Target": "Parameter",
      "Id": "PARAM_TEAR_03_MOVE",
      "FadeInTime": -1.0,
      "FadeOutTime": -1.0,
      "Segments": [
        0,
        0,
        0,
        2.9,
        0
      ]
    },
    {
      "Target": "Parameter",
      "Id": "PARAM_SWEAT",
      "FadeInTime": -1.0,
      "FadeOutTime": -1.0,
      "Segments": [
        0,
        0,
        0,
        2.9,
        0
      ]
    },
    {
      "Target": "Parameter",
      "Id": "PARAM_SWEAT_MOVE",
      "FadeInTime": -1.0,
      "FadeOutTime": -1.0,
      "Segments": [
        0,
        0,
        0,
        2.9,
        0
      ]
    },
    {
      "Target": "Parameter",
      "Id": "PARAM_EYE_WHITE_00",
      "FadeInTime": -1.0,
      "FadeOutTime": -1.0,
      "Segments": [
        0,
        1,
        0,
        2.9,
        1
      ]
    },
    {
      "Target": "Parameter",
      "Id": "PARAM_EYE_WHITE_01",
      "FadeInTime": -1.0,
      "FadeOutTime": -1.0,
      "Segments": [
        0,
        0,
        0,
        2.9,
        0
      ]
    },
    {
      "Target": "Parameter",
      "Id": "PARAM_EYE_01",
      "FadeInTime": -1.0,
      "FadeOutTime": -1.0,
      "Segments": [
        0,
        1,
        0,
        2.9,
        1
      ]
    },
    {
      "Target": "Parameter",
      "Id": "PARAM_EYE_02",
      "FadeInTime": -1.0,
      "FadeOutTime": -1.0,
      "Segments": [
        0,
        0,
        0,
        2.9,
        0
      ]
    },
    {
      "Target": "Parameter",
      "Id": "PARAM_EYE_05",
      "FadeInTime": -1.0,
      "FadeOutTime": -1.0,
      "Segments": [
        0,
        0,
        0,
        2.9,
        0
      ]
    },
    {
      "Target": "Parameter",
      "Id": "PARAM_MOUTH_01",
      "FadeInTime": -1.0,
      "FadeOutTime": -1.0,
      "Segments": [
        0,
        1,
        0,
        2.9,
        1
      ]
    },
    {
      "Target": "Parameter",
      "Id": "PARAM_MOUTH_02",
      "FadeInTime": -1.0,
      "FadeOutTime": -1.0,
      "Segments": [
        0,
        0,
        0,
        2.9,
        0
      ]
    },
    {
      "Target": "Parameter",
      "Id": "PARAM_MOUTH_03",
      "FadeInTime": -1.0,
      "FadeOutTime": -1.0,
      "Segments": [
        0,
        0,
        0,
        2.9,
        0
      ]
    },
    {
      "Target": "Parameter",
      "Id": "PARAM_MOUTH_05",
      "FadeInTime": -1.0,
      "FadeOutTime": -1.0,
      "Segments": [
        0,
        0,
        0,
        2.9,
        0
      ]
    },
    {
      "Target": "Parameter",
      "Id": "PARAM_BROW_01",
      "FadeInTime": -1.0,
      "FadeOutTime": -1.0,
      "Segments": [
        0,
        1,
        0,
        2.9,
        1
      ]
    },
    {
      "Target": "Parameter",
      "Id": "PARAM_HAND_R_01",
      "FadeInTime": -1.0,
      "FadeOutTime": -1.0,
      "Segments": [
        0,
        0,
        0,
        2.9,
        0
      ]
    },
    {
      "Target": "Parameter",
      "Id": "PARAM_HAND_R_02",
      "FadeInTime": -1.0,
      "FadeOutTime": -1.0,
      "Segments": [
        0,
        0,
        0,
        2.9,
        0
      ]
    },
    {
      "Target": "Parameter",
      "Id": "PARAM_HAND_R_03",
      "FadeInTime": -1.0,
      "FadeOutTime": -1.0,
      "Segments": [
        0,
        0,
        0,
        2.9,
        0
      ]
    },
    {
      "Target": "Parameter",
      "Id": "PARAM_HAND_R_04",
      "FadeInTime": -1.0,
      "FadeOutTime": -1.0,
      "Segments": [
        0,
        0,
        0,
        2.9,
        0
      ]
    },
    {
      "Target": "Parameter",
      "Id": "PARAM_HAND_R_05",
      "FadeInTime": -1.0,
      "FadeOutTime": -1.0,
      "Segments": [
        0,
        0,
        0,
        2.9,
        0
      ]
    },
    {
      "Target": "Parameter",
      "Id": "PARAM_HAND_R_06",
      "FadeInTime": -1.0,
      "FadeOutTime": -1.0,
      "Segments": [
        0,
        0,
        0,
        2.9,
        0
      ]
    },
    {
      "Target": "Parameter",
      "Id": "PARAM_HAND_R_07",
      "FadeInTime": -1.0,
      "FadeOutTime": -1.0,
      "Segments": [
        0,
        0,
        0,
        2.9,
        0
      ]
    },
    {
      "Target": "Parameter",
      "Id": "PARAM_HAND_R_08",
      "FadeInTime": -1.0,
      "FadeOutTime": -1.0,
      "Segments": [
        0,
        0,
        0,
        2.9,
        0
      ]
    },
    {
      "Target": "Parameter",
      "Id": "PARAM_HAND_R_09",
      "FadeInTime": -1.0,
      "FadeOutTime": -1.0,
      "Segments": [
        0,
        1,
        0,
        2.9,
        1
      ]
    },
    {
      "Target": "Parameter",
      "Id": "PARAM_HAND_R_10",
      "FadeInTime": -1.0,
      "FadeOutTime": -1.0,
      "Segments": [
        0,
        0,
        0,
        2.9,
        0
      ]
    },
    {
      "Target": "Parameter",
      "Id": "PARAM_HAND_R_11",
      "FadeInTime": -1.0,
      "FadeOutTime": -1.0,
      "Segments": [
        0,
        0,
        0,
        2.9,
        0
      ]
    },
    {
      "Target": "Parameter",
      "Id": "PARAM_HAND_L_01",
      "FadeInTime": -1.0,
      "FadeOutTime": -1.0,
      "Segments": [
        0,
        0,
        0,
        2.9,
        0
      ]
    },
    {
      "Target": "Parameter",
      "Id": "PARAM_HAND_L_02",
      "FadeInTime": -1.0,
      "FadeOutTime": -1.0,
      "Segments": [
        0,
        0,
        0,
        2.9,
        0
      ]
    },
    {
      "Target": "Parameter",
      "Id": "PARAM_HAND_L_03",
      "FadeInTime": -1.0,
      "FadeOutTime": -1.0,
      "Segments": [
        0,
        0,
        0,
        2.9,
        0
      ]
    },
    {
      "Target": "Parameter",
      "Id": "PARAM_HAND_L_04",
      "FadeInTime": -1.0,
      "FadeOutTime": -1.0,
      "Segments": [
        0,
        0,
        0,
        2.9,
        0
      ]
    },
    {
      "Target": "Parameter",
      "Id": "PARAM_HAND_L_05",
      "FadeInTime": -1.0,
      "FadeOutTime": -1.0,
      "Segments": [
        0,
        0,
        0,
        2.9,
        0
      ]
    },
    {
      "Target": "Parameter",
      "Id": "PARAM_HAND_L_06",
      "FadeInTime": -1.0,
      "FadeOutTime": -1.0,
      "Segments": [
        0,
        0,
        0,
        2.9,
        0
      ]
    },
    {
      "Target": "Parameter",
      "Id": "PARAM_HAND_L_07",
      "FadeInTime": -1.0,
      "FadeOutTime": -1.0,
      "Segments": [
        0,
        0,
        0,
        2.9,
        0
      ]
    },
    {
      "Target": "Parameter",
      "Id": "PARAM_HAND_L_08",
      "FadeInTime": -1.0,
      "FadeOutTime": -1.0,
      "Segments": [
        0,
        0,
        0,
        2.9,
        0
      ]
    },
    {
      "Target": "Parameter",
      "Id": "PARAM_HAND_L_09",
      "FadeInTime": -1.0,
      "FadeOutTime": -1.0,
      "Segments": [
        0,
        0,
        0,
        2.9,
        0
      ]
    },
    {
      "Target": "Parameter",
      "Id": "PARAM_HAND_L_10",
      "FadeInTime": -1.0,
      "FadeOutTime": -1.0,
      "Segments": [
        0,
        1,
        0,
        2.9,
        1
      ]
    },
    {
      "Target": "Parameter",
      "Id": "PARAM_HAND_L_11",
      "FadeInTime": -1.0,
      "FadeOutTime": -1.0,
      "Segments": [
        0,
        0,
        0,
        2.9,
        0
      ]
    },
    {
      "Target": "Parameter",
      "Id": "PARAM_UPPER_BODY_FLUFFY",
      "FadeInTime": -1.0,
      "FadeOutTime": -1.0,
      "Segments": [
        0,
        0,
        0,
        2.9,
        0
      ]
    },
    {
      "Target": "Parameter",
      "Id": "PARAM_LOWER_BODY_FLUFFY",
      "FadeInTime": -1.0,
      "FadeOutTime": -1.0,
      "Segments": [
        0,
        0,
        0,
        2.9,
        0
      ]
    },
    {
      "Target": "PartOpacity",
      "Id": "PartFrontHair",
      "FadeInTime": -1.0,
      "FadeOutTime": -1.0,
      "Segments": [
        0,
        1,
        0,
        2.9,
        1
      ]
    },
    {
      "Target": "PartOpacity",
      "Id": "PartEyebrow",
      "FadeInTime": -1.0,
      "FadeOutTime": -1.0,
      "Segments": [
        0,
        1,
        0,
        2.9,
        1
      ]
    },
    {
      "Target": "PartOpacity",
      "Id": "PartMouth",
      "FadeInTime": -1.0,
      "FadeOutTime": -1.0,
      "Segments": [
        0,
        1,
        0,
        2.9,
        1
      ]
    },
    {
      "Target": "PartOpacity",
      "Id": "PartEyeL",
      "FadeInTime": -1.0,
      "FadeOutTime": -1.0,
      "Segments": [
        0,
        1,
        0,
        2.9,
        1
      ]
    },
    {
      "Target": "PartOpacity",
      "Id": "PartEyeR",
      "FadeInTime": -1.0,
      "FadeOutTime": -1.0,
      "Segments": [
        0,
        1,
        0,
        2.9,
        1
      ]
    },
    {
      "Target": "PartOpacity",
      "Id": "PartCheek",
      "FadeInTime": -1.0,
      "FadeOutTime": -1.0,
      "Segments": [
        0,
        1,
        0,
        2.9,
        1
      ]
    },
    {
      "Target": "PartOpacity",
      "Id": "PartHead",
      "FadeInTime": -1.0,
      "FadeOutTime": -1.0,
      "Segments": [
        0,
        1,
        0,
        2.9,
        1
      ]
    },
    {
      "Target": "PartOpacity",
      "Id": "PartBackHair",
      "FadeInTime": -1.0,
      "FadeOutTime": -1.0,
      "Segments": [
        0,
        1,
        0,
        2.9,
        1
      ]
    },
    {
      "Target": "PartOpacity",
      "Id": "PartExpression",
      "FadeInTime": -1.0,
      "FadeOutTime": -1.0,
      "Segments": [
        0,
        1,
        0,
        2.9,
        1
      ]
    },
    {
      "Target": "PartOpacity",
      "Id": "PartNeck",
      "FadeInTime": -1.0,
      "FadeOutTime": -1.0,
      "Segments": [
        0,
        1,
        0,
        2.9,
        1
      ]
    },
    {
      "Target": "PartOpacity",
      "Id": "PartUpperBody",
      "FadeInTime": -1.0,
      "FadeOutTime": -1.0,
      "Segments": [
        0,
        1,
        0,
        2.9,
        1
      ]
    },
    {
      "Target": "PartOpacity",
      "Id": "PartArmR",
      "FadeInTime": -1.0,
      "FadeOutTime": -1.0,
      "Segments": [
        0,
        1,
        0,
        2.9,
        1
      ]
    },
    {
      "Target": "PartOpacity",
      "Id": "PartHandR",
      "FadeInTime": -1.0,
      "FadeOutTime": -1.0,
      "Segments": [
        0,
        1,
        0,
        2.9,
        1
      ]
    },
    {
      "Target": "PartOpacity",
      "Id": "PartLowerBody",
      "FadeInTime": -1.0,
      "FadeOutTime": -1.0,
      "Segments": [
        0,
        1,
        0,
        2.9,
        1
      ]
    },
    {
      "Target": "PartOpacity",
      "Id": "PartFoot",
      "FadeInTime": -1.0,
      "FadeOutTime": -1.0,
      "Segments": [
        0,
        1,
        0,
        2.9,
        1
      ]
    }
  ],
  "UserData": []
}